cliquepicking-0.3.2.dist-info/METADATA
cliquepicking-0.3.2.dist-info/WHEEL
cliquepicking/__init__.py
cliquepicking/__init__.pyi
cliquepicking/cliquepicking.cpython-310-x86_64-linux-gnu.so
cliquepicking/py.typed
cliquepicking-0.3.2.dist-info/RECORD
