Metadata-Version: 2.4
Name: cliquepicking
Version: 0.3.2
Classifier: Programming Language :: Rust
Classifier: Programming Language :: Python :: Implementation :: CPython
Classifier: Programming Language :: Python :: Implementation :: PyPy
Summary: Counting, Sampling and Listing Markov Equivalent DAGs
Keywords: causality,causal discovery,markov equivalence
Author: Marcel Wienöbst
Requires-Python: >=3.8
